Metadata-Version: 1.1
Name: Mopidy-IRControl
Version: 0.1.0
Summary: Mopidy frontend to be controlled with an IR controller
Home-page: https://github.com/spjoe/mopidy-ircontrol
Author: Camillo Dell'mour
Author-email: cdellmour@gmail.com
License: Apache License, Version 2.0
Platform: UNKNOWN
Classifier: Environment :: No Input/Output (Daemon)
Classifier: Intended Audience :: End Users/Desktop
Classifier: License :: OSI Approved :: Apache Software License
Classifier: Operating System :: OS Independent
Classifier: Programming Language :: Python :: 2
Classifier: Topic :: Multimedia :: Sound/Audio :: Players
